image_generator.py
stable_diffusion_gateway.py
zk_rag_image_generator-1.1.0.dist-info/METADATA
zk_rag_image_generator-1.1.0.dist-info/WHEEL
zk_rag_image_generator-1.1.0.dist-info/entry_points.txt
zk_rag_image_generator-1.1.0.dist-info/top_level.txt
zk_rag_image_generator-1.1.0.dist-info/RECORD
