Metadata-Version: 2.2
Name: zk-rag-image-generator
Version: 1.1.0
Summary: Tool plugin for zk-rag to generate images with stable diffusion 3.5 medium
Author-email: Stacey Vetzal <stacey@vetzal.com>
Classifier: Programming Language :: Python :: 3
Classifier: License :: OSI Approved :: MIT License
Classifier: Operating System :: OS Independent
Requires-Python: >=3.11
Requires-Dist: mojentic>=0.2.5
Requires-Dist: torch
Requires-Dist: torchvision
Requires-Dist: torchaudio
Requires-Dist: diffusers
Requires-Dist: transformers
Requires-Dist: accelerate
Requires-Dist: safetensors
Requires-Dist: scipy
Requires-Dist: protobuf
Requires-Dist: sentencepiece
